2024102024/VERILOG/cla.v

module cla_5bit(
    output cout,
    output reg [4:0] sum,
    input [4:0] a_in, b_in,
    input cin, clk
);
    reg [4:0] a, b;
    wire [4:0] sum_comb;

    //DFF impelentation for inputs
    always @(posedge clk) begin
        a <= a_in;
        b <= b_in;
    end

    wire p4, p3, p2, p1, p0;
    wire g4, g3, g2, g1, g0;
    
    and (g4, a[4], b[4]);
    and (g3, a[3], b[3]);
    and (g2, a[2], b[2]);
    and (g1, a[1], b[1]);
    and (g0, a[0], b[0]);

    xor (p4, a[4], b[4]);
    xor (p3, a[3], b[3]);
    xor (p2, a[2], b[2]);
    xor (p1, a[1], b[1]);
    xor (p0, a[0], b[0]);

    wire c0, c1, c2, c3, c4;
    wire p0_and_cin, p1_and_g0, p1_p0_and_cin;
    wire p2_and_g1, p2_p1_and_g0, p2_p1_p0_and_cin;
    wire p3_and_g2, p3_p2_and_g1, p3_p2_p1_and_g0, p3_p2_p1_p0_and_cin;
    wire p4_and_g3, p4_p3_and_g2, p4_p3_p2_and_g1, p4_p3_p2_p1_and_g0, p4_p3_p2_p1_p0_and_cin;

    // C0 calculation
    and (p0_and_cin, p0, cin);
    or  (c0, g0, p0_and_cin);

    // C1 calculation
    and (p1_and_g0, p1, g0);
    and (p1_p0_and_cin, p1, p0, cin);
    or  (c1, g1, p1_and_g0, p1_p0_and_cin);

    // C2 calculation
    and (p2_and_g1, p2, g1);
    and (p2_p1_and_g0, p2, p1, g0);
    and (p2_p1_p0_and_cin, p2, p1, p0, cin);
    or  (c2, g2, p2_and_g1, p2_p1_and_g0, p2_p1_p0_and_cin);

    // C3 calculation
    and (p3_and_g2, p3, g2);
    and (p3_p2_and_g1, p3, p2, g1);
    and (p3_p2_p1_and_g0, p3, p2, p1, g0);
    and (p3_p2_p1_p0_and_cin, p3, p2, p1, p0, cin);
    or  (c3, g3, p3_and_g2, p3_p2_and_g1, p3_p2_p1_and_g0, p3_p2_p1_p0_and_cin);

    // C4 calculation
    and (p4_and_g3, p4, g3);
    and (p4_p3_and_g2, p4, p3, g2);
    and (p4_p3_p2_and_g1, p4, p3, p2, g1);
    and (p4_p3_p2_p1_and_g0, p4, p3, p2, p1, g0);
    and (p4_p3_p2_p1_p0_and_cin, p4, p3, p2, p1, p0, cin);
    or  (c4, g4, p4_and_g3, p4_p3_and_g2, p4_p3_p2_and_g1, p4_p3_p2_p1_and_g0, p4_p3_p2_p1_p0_and_cin);

    // C5 calculation (cout)
    and (p4_and_g3, p4, g3);
    and (p4_p3_and_g2, p4, p3, g2);
    and (p4_p3_p2_and_g1, p4, p3, p2, g1);
    and (p4_p3_p2_p1_and_g0, p4, p3, p2, p1, g0);
    and (p4_p3_p2_p1_p0_and_cin, p4, p3, p2, p1, p0, cin);
    or  (cout, g4, p4_and_g3, p4_p3_and_g2, p4_p3_p2_and_g1, p4_p3_p2_p1_and_g0, p4_p3_p2_p1_p0_and_cin);

    // Sum calculation
    xor (sum_comb[0], p0, cin);
    xor (sum_comb[1], p1, c0);
    xor (sum_comb[2], p2, c1);
    xor (sum_comb[3], p3, c2);
    xor (sum_comb[4], p4, c3);

    //DFF for outputs
    always @(posedge clk) begin
        sum <= sum_comb;
    end
endmodule

2024102024/VERILOG/cla_tb.v

module cla_5bit_tb;
    reg [4:0] a_in, b_in;
    reg cin, clk;
    wire [4:0] sum;
    wire cout;

    cla_5bit uut (
        .cout(cout),
        .sum(sum),
        .a_in(a_in),
        .b_in(b_in),
        .cin(cin),
        .clk(clk)
    );

    initial begin
        clk = 0;
        forever #7 clk = ~clk;
    end

    initial begin
        $dumpfile("dump_cla_adder.vcd");
        $dumpvars(0, cla_5bit_tb);

        a_in = 0;
        b_in = 0;
        cin = 0;
        #100;     
        
        @(posedge clk);
        a_in = 5'b00001;
        b_in = 5'b00001;
        #100;    
        
        @(posedge clk);
        a_in = 5'b01111;
        b_in = 5'b00001;
        #100;
        
        @(posedge clk);
        a_in = 5'b10101;
        b_in = 5'b01010;
        #100;
        
        @(posedge clk);
        a_in = 5'b10000;
        b_in = 5'b01111;
        #100;

        @(posedge clk);
        a_in = 5'b11111;
        b_in = 5'b11111;
        #100;
        
        #100;
        
        $finish;
    end

    initial begin
        $monitor("Time=%0t a_in=%b b_in=%b cin=%b sum=%b cout=%b",
                 $time, a_in, b_in, cin, sum, cout);
    end
endmodule

2024102024/VERILOG/dump_cla_adder.vcd
$date
	Wed Dec  3 22:30:18 2025
$end
$version
	Icarus Verilog
$end
$timescale
	1s
$end
$scope module cla_5bit_tb $end
$var wire 5 ! sum [4:0] $end
$var wire 1 " cout $end
$var reg 5 # a_in [4:0] $end
$var reg 5 $ b_in [4:0] $end
$var reg 1 % cin $end
$var reg 1 & clk $end
$scope module uut $end
$var wire 5 ' a_in [4:0] $end
$var wire 5 ( b_in [4:0] $end
$var wire 1 ) c0 $end
$var wire 1 * c1 $end
$var wire 1 + c2 $end
$var wire 1 , c3 $end
$var wire 1 - c4 $end
$var wire 1 % cin $end
$var wire 1 & clk $end
$var wire 1 " cout $end
$var wire 1 . g0 $end
$var wire 1 / g1 $end
$var wire 1 0 g2 $end
$var wire 1 1 g3 $end
$var wire 1 2 g4 $end
$var wire 1 3 p0 $end
$var wire 1 4 p0_and_cin $end
$var wire 1 5 p1 $end
$var wire 1 6 p1_and_g0 $end
$var wire 1 7 p1_p0_and_cin $end
$var wire 1 8 p2 $end
$var wire 1 9 p2_and_g1 $end
$var wire 1 : p2_p1_and_g0 $end
$var wire 1 ; p2_p1_p0_and_cin $end
$var wire 1 < p3 $end
$var wire 1 = p3_and_g2 $end
$var wire 1 > p3_p2_and_g1 $end
$var wire 1 ? p3_p2_p1_and_g0 $end
$var wire 1 @ p3_p2_p1_p0_and_cin $end
$var wire 1 A p4 $end
$var wire 1 B p4_and_g3 $end
$var wire 1 C p4_p3_and_g2 $end
$var wire 1 D p4_p3_p2_and_g1 $end
$var wire 1 E p4_p3_p2_p1_and_g0 $end
$var wire 1 F p4_p3_p2_p1_p0_and_cin $end
$var wire 5 G sum_comb [4:0] $end
$var reg 5 H a [4:0] $end
$var reg 5 I b [4:0] $end
$var reg 5 J sum [4:0] $end
$upscope $end
$upscope $end
$enddefinitions $end
$comment Show the parameter values. $end
$dumpall
$end
#0
$dumpvars
bx J
bx I
bx H
bx G
0F
xE
xD
xC
xB
xA
0@
x?
x>
x=
x<
0;
x:
x9
x8
07
x6
x5
04
x3
x2
x1
x0
x/
x.
x-
x,
x+
x*
x)
b0 (
b0 '
0&
0%
b0 $
b0 #
x"
bx !
$end
#7
0-
0"
0,
0E
0+
0*
0)
0B
0=
0C
09
0>
0D
06
0:
0?
b0 G
02
01
00
0/
0.
0A
0<
08
05
03
b0 I
b0 H
1&
#14
0&
#21
b0 !
b0 J
1&
#28
0&
#35
1&
#42
0&
#49
1&
#56
0&
#63
1&
#70
0&
#77
1&
#84
0&
#91
1&
#98
0&
#105
b10 G
1)
1.
b1 I
b1 H
b1 $
b1 (
b1 #
b1 '
1&
#112
0&
#119
b10 !
b10 J
1&
#126
0&
#133
1&
#140
0&
#147
1&
#154
0&
#161
1&
#168
0&
#175
1&
#182
0&
#189
1&
#196
0&
#203
1&
#210
0&
#217
1,
1*
1+
16
1:
1?
b10000 G
1<
18
15
b1111 H
b1111 #
b1111 '
1&
#224
0&
#231
b10000 !
b10000 J
1&
#238
0&
#245
1&
#252
0&
#259
1&
#266
0&
#273
1&
#280
0&
#287
1&
#294
0&
#301
1&
#308
0&
#315
1&
#322
0&
#329
0,
0*
0+
0)
06
0:
0?
b11111 G
0.
13
1A
b1010 I
b10101 H
b1010 $
b1010 (
b10101 #
b10101 '
1&
#336
0&
#343
b11111 !
b11111 J
1&
#350
0&
#357
1&
#364
0&
#371
1&
#378
0&
#385
1&
#392
0&
#399
1&
#406
0&
#413
1&
#420
0&
#427
1&
#434
0&
#441
b1111 I
b10000 H
b1111 $
b1111 (
b10000 #
b10000 '
1&
#448
0&
#455
1&
#462
0&
#469
1&
#476
0&
#483
1&
#490
0&
#497
1&
#504
0&
#511
1&
#518
0&
#525
1&
#532
0&
#539
1&
#546
0&
#553
1-
1"
1,
1+
1*
1)
b11110 G
12
0A
11
10
1/
1.
0<
08
05
03
b11111 I
b11111 H
b11111 $
b11111 (
b11111 #
b11111 '
1&
#560
0&
#567
b11110 !
b11110 J
1&
